chocobo/__init__.py
chocobo/chocobo.py
chocobo-0.0.4.dist-info/LICENSE
chocobo-0.0.4.dist-info/METADATA
chocobo-0.0.4.dist-info/WHEEL
chocobo-0.0.4.dist-info/top_level.txt
chocobo-0.0.4.dist-info/RECORD
